flask_typed/__init__.py
flask_typed/annotations.py
flask_typed/docs/__init__.py
flask_typed/docs/responses.py
flask_typed/docs/utils.py
flask_typed/errors.py
flask_typed/handler.py
flask_typed/parameter.py
flask_typed/parsers.py
flask_typed/response.py
flask_typed/typed_api.py
flask_typed/typed_resource.py
flask_typed/validators.py
flask_typed-0.2.3.dist-info/LICENSE
flask_typed-0.2.3.dist-info/METADATA
flask_typed-0.2.3.dist-info/WHEEL
flask_typed-0.2.3.dist-info/RECORD
