Metadata-Version: 2.1
Name: flask-typed
Version: 0.2.3
Summary: 
Author: Mustafa Efendioğlu
Author-email: mfnd@protonmail.com
Requires-Python: >=3.10,<4.0
Classifier: Programming Language :: Python :: 3
Classifier: Programming Language :: Python :: 3.10
Classifier: Programming Language :: Python :: 3.11
Classifier: Programming Language :: Python :: 3.12
Requires-Dist: docstring-parser (>=0.15,<0.16)
Requires-Dist: flask (>=2.2.3)
Requires-Dist: openapi-pydantic (>=0.4.0,<0.5.0)
Requires-Dist: pydantic (>=2.5.3,<3.0.0)
